{"info":{"count":826,"pages":42,"next":"https://rickandmortyapi.com/api/character/?page=21","prev":"https://rickandmortyapi.com/api/character/?page=19"},"results":[{"id":391,"name":"Uncle Steve","status":"Dead","species":"Alien","type":"Parasite","gender":"Male","origin":{"name":"unknown","url":""},"location":{"name":"Earth (Replacement Dimension)","url":"https://rickandmortyapi.com/api/location/20"},"image":"https://rickandmortyapi.com/api/character/avatar/391.jpeg","episode":["https://rickandmortyapi.com/api/episode/15"],"url":"https://rickandmortyapi.com/api/character/391","created":"2018-01-14T13:34:50.096Z"},{"id":392,"name":"Bearded Morty","status":"Alive","species":"Human","type":"","gender":"Male","origin":{"name":"unknown","url":""},"location":{"name":"Citadel of Ricks","url":"https://rickandmortyapi.com/api/location/3"},"image":"https://rickandmortyapi.com/api/character/avatar/392.jpeg","episode":["https://rickandmortyapi.com/api/episode/28","https://rickandmortyapi.com/api/episode/51"],"url":"https://rickandmortyapi.com/api/character/392","created":"2018-01-14T14:48:05.977Z"},{"id":393,"name":"Roy","status":"Alive","species":"Human","type":"Game","gender":"Male","origin":{"name":"Roy: A Life Well Lived","url":"https://rickandmortyapi.com/api/location/32"},"location":{"name":"Roy: A Life Well Lived","url":"https://rickandmortyapi.com/api/location/32"},"image":"https://rickandmortyapi.com/api/character/avatar/393.jpeg","episode":["https://rickandmortyapi.com/api/episode/13"],"url":"https://rickandmortyapi.com/api/character/393","created":"2018-01-20T19:15:27.239Z"},{"id":394,"name":"Davin","status":"Dead","species":"Cronenberg","type":"","gender":"Male","origin":{"name":"Earth (C-137)","url":"https://rickandmortyapi.com/api/location/1"},"location":{"name":"Earth (C-137)","url":"https://rickandmortyapi.com/api/location/1"},"image":"https://rickandmortyapi.com/api/character/avatar/394.jpeg","episode":["https://rickandmortyapi.com/api/episode/1","https://rickandmortyapi.com/api/episode/6"],"url":"https://rickandmortyapi.com/api/character/394","created":"2018-01-20T19:48:42.201Z"},{"id":395,"name":"Greebybobe","status":"Alive","species":"Alien","type":"Greebybobe","gender":"unknown","origin":{"name":"Girvonesk","url":"https://rickandmortyapi.com/api/location/68"},"location":{"name":"Worldender's lair","url":"https://rickandmortyapi.com/api/location/4"},"image":"https://rickandmortyapi.com/api/character/avatar/395.jpeg","episode":["https://rickandmortyapi.com/api/episode/1","https://rickandmortyapi.com/api/episode/11","https://rickandmortyapi.com/api/episode/16","https://rickandmortyapi.com/api/episode/25"],"url":"https://rickandmortyapi.com/api/character/395","created":"2018-04-15T16:46:31.715Z"},{"id":396,"name":"Scary Teacher","status":"Alive","species":"Mythological Creature","type":"Monster","gender":"Male","origin":{"name":"Mr. Goldenfold's dream","url":"https://rickandmortyapi.com/api/location/18"},"location":{"name":"Mr. Goldenfold's dream","url":"https://rickandmortyapi.com/api/location/18"},"image":"https://rickandmortyapi.com/api/character/avatar/396.jpeg","episode":["https://rickandmortyapi.com/api/episode/2"],"url":"https://rickandmortyapi.com/api/character/396","created":"2018-04-15T17:10:07.639Z"},{"id":397,"name":"Fido","status":"Alive","species":"Animal","type":"Dog","gender":"Male","origin":{"name":"Snuffles' Dream","url":"https://rickandmortyapi.com/api/location/70"},"location":{"name":"Snuffles' Dream","url":"https://rickandmortyapi.com/api/location/70"},"image":"https://rickandmortyapi.com/api/character/avatar/397.jpeg","episode":["https://rickandmortyapi.com/api/episode/2"],"url":"https://rickandmortyapi.com/api/character/397","created":"2018-04-15T17:15:28.777Z"},{"id":398,"name":"Accountant dog","status":"Alive","species":"Animal","type":"Dog","gender":"Male","origin":{"name":"Snuffles' Dream","url":"https://rickandmortyapi.com/api/location/70"},"location":{"name":"Snuffles' Dream","url":"https://rickandmortyapi.com/api/location/70"},"image":"https://rickandmortyapi.com/api/character/avatar/398.jpeg","episode":["https://rickandmortyapi.com/api/episode/2"],"url":"https://rickandmortyapi.com/api/character/398","created":"2018-04-15T17:23:04.169Z"},{"id":399,"name":"Tiny-persons advocacy group lawyer","status":"Alive","species":"Mythological Creature","type":"Giant","gender":"Male","origin":{"name":"Giant's Town","url":"https://rickandmortyapi.com/api/location/14"},"location":{"name":"Giant's Town","url":"https://rickandmortyapi.com/api/location/14"},"image":"https://rickandmortyapi.com/api/character/avatar/399.jpeg","episode":["https://rickandmortyapi.com/api/episode/5"],"url":"https://rickandmortyapi.com/api/character/399","created":"2018-04-15T17:34:02.076Z"},{"id":400,"name":"Giant Judge","status":"Alive","species":"Mythological Creature","type":"Giant","gender":"Male","origin":{"name":"Giant's Town","url":"https://rickandmortyapi.com/api/location/14"},"location":{"name":"Giant's Town","url":"https://rickandmortyapi.com/api/location/14"},"image":"https://rickandmortyapi.com/api/character/avatar/400.jpeg","episode":["https://rickandmortyapi.com/api/episode/5"],"url":"https://rickandmortyapi.com/api/character/400","created":"2018-04-15T17:36:11.295Z"}]}